asset_model/__init__.py
asset_model/asset.py
asset_model/oam_object.py
asset_model/property.py
asset_model/relation.py
asset_model/utils.py
asset_model/account/__init__.py
asset_model/account/account.py
asset_model/account/account_test.py
asset_model/certificate/__init__.py
asset_model/certificate/tls_certificate.py
asset_model/certificate/tls_certificate_test.py
asset_model/contact/__init__.py
asset_model/contact/contact_record.py
asset_model/contact/contact_record_test.py
asset_model/contact/location.py
asset_model/contact/location_test.py
asset_model/contact/phone.py
asset_model/contact/phone_test.py
asset_model/dns/__init__.py
asset_model/dns/dns_record.py
asset_model/dns/dns_record_test.py
asset_model/dns/fqdn.py
asset_model/dns/fqdn_test.py
asset_model/file/__init__.py
asset_model/file/file.py
asset_model/file/file_test.py
asset_model/financial/__init__.py
asset_model/financial/funds_transfer.py
asset_model/financial/funds_transfer_test.py
asset_model/general/__init__.py
asset_model/general/identifier.py
asset_model/general/identifier_test.py
asset_model/general/port.py
asset_model/general/port_test.py
asset_model/general/simple.py
asset_model/general/simple_test.py
asset_model/general/source.py
asset_model/general/source_test.py
asset_model/network/__init__.py
asset_model/network/autonomous_system.py
asset_model/network/autonomous_system_test.py
asset_model/network/ip_address.py
asset_model/network/ip_address_test.py
asset_model/network/netblock.py
asset_model/network/netblock_test.py
asset_model/org/__init__.py
asset_model/org/org.py
asset_model/org/org_test.py
asset_model/people/__init__.py
asset_model/people/person.py
asset_model/people/person_test.py
asset_model/pf/__init__.py
asset_model/pf/product.py
asset_model/pf/product_test.py
asset_model/pf/service.py
asset_model/pf/service_test.py
asset_model/pf/vuln.py
asset_model/pf/vuln_test.py
asset_model/registration/__init__.py
asset_model/registration/autnum_record.py
open_asset_model-1.1.1.dist-info/METADATA
open_asset_model-1.1.1.dist-info/WHEEL
open_asset_model-1.1.1.dist-info/licenses/LICENSE
open_asset_model-1.1.1.dist-info/RECORD
