Metadata-Version: 2.4
Name: open-asset-model
Version: 1.1.1
Summary: A Python implementation of the Open Asset Model.
Project-URL: Homepage, https://github.com/0ppliger/open-asset-model.py
Project-URL: Issues, https://github.com/0ppliger/open-asset-model.py/issues
Author-email: "J. Oppliger" <julien@oppliger.cc>
License-Expression: Apache-2.0
License-File: LICENSE
Classifier: Operating System :: OS Independent
Classifier: Programming Language :: Python :: 3
Requires-Python: >=3.10
Requires-Dist: fqdn
Requires-Dist: phonenumbers
